testproject_1/__init__.py
testproject_1/empty.py
testproject_1-0.1.1.dist-info/METADATA
testproject_1-0.1.1.dist-info/WHEEL
testproject_1-0.1.1.dist-info/RECORD
