Metadata-Version: 2.3
Name: testproject_1
Version: 0.1.1
Summary: test project for trusted publisher.
Project-URL: Homepage, https://github.com/popenta/test-repo
Author: p0pe
Requires-Python: >=3.8
